class_registry/__init__.py
class_registry/auto_register.py
class_registry/cache.py
class_registry/entry_points.py
class_registry/patcher.py
class_registry/registry.py
class_registry-2.1.2.dist-info/DESCRIPTION.rst
class_registry-2.1.2.dist-info/METADATA
class_registry-2.1.2.dist-info/RECORD
class_registry-2.1.2.dist-info/WHEEL
class_registry-2.1.2.dist-info/metadata.json
class_registry-2.1.2.dist-info/top_level.txt
