Metadata-Version: 1.1
Name: class-registry
Version: 2.1.2
Summary: Factory+Registry pattern for Python classes.
Home-page: https://class-registry.readthedocs.io/
Author: Phoenix Zerin
Author-email: phoenix.zerin@eflglobal.com
License: MIT
Keywords: registry pattern
Platform: UNKNOWN
Classifier: Development Status :: 5 - Production/Stable
Classifier: Intended Audience :: Developers
Classifier: License :: OSI Approved :: MIT License
Classifier: Programming Language :: Python :: 2
Classifier: Programming Language :: Python :: 2.7
Classifier: Programming Language :: Python :: 3
Classifier: Programming Language :: Python :: 3.5
Classifier: Programming Language :: Python :: 3.6
Classifier: Topic :: Software Development :: Libraries :: Python Modules
